LICENSE
MANIFEST.in
README.md
setup.py
G2lib/_G2lib.cp310-win_amd64.pyd
G2lib/_G2lib.cp311-win_amd64.pyd
G2lib/_G2lib.cp312-win_amd64.pyd
G2lib/_G2lib.cp36-win_amd64.pyd
G2lib/_G2lib.cp37-win_amd64.pyd
G2lib/_G2lib.cp38-win_amd64.pyd
G2lib/_G2lib.cp39-win_amd64.pyd
G2lib/_G2lib.cpython-310-x86_64-linux-gnu.so
G2lib/_G2lib.cpython-311-x86_64-linux-gnu.so
G2lib/_G2lib.cpython-312-x86_64-linux-gnu.so
G2lib/_G2lib.cpython-36m-x86_64-linux-gnu.so
G2lib/_G2lib.cpython-37m-x86_64-linux-gnu.so
G2lib/_G2lib.cpython-38-x86_64-linux-gnu.so
G2lib/_G2lib.cpython-39-x86_64-linux-gnu.so
G2lib/_G2lib_Interpolation.cp310-win_amd64.pyd
G2lib/_G2lib_Interpolation.cp311-win_amd64.pyd
G2lib/_G2lib_Interpolation.cp312-win_amd64.pyd
G2lib/_G2lib_Interpolation.cp36-win_amd64.pyd
G2lib/_G2lib_Interpolation.cp37-win_amd64.pyd
G2lib/_G2lib_Interpolation.cp38-win_amd64.pyd
G2lib/_G2lib_Interpolation.cp39-win_amd64.pyd
G2lib/_G2lib_Interpolation.cpython-310-x86_64-linux-gnu.so
G2lib/_G2lib_Interpolation.cpython-311-x86_64-linux-gnu.so
G2lib/_G2lib_Interpolation.cpython-312-x86_64-linux-gnu.so
G2lib/_G2lib_Interpolation.cpython-36m-x86_64-linux-gnu.so
G2lib/_G2lib_Interpolation.cpython-37m-x86_64-linux-gnu.so
G2lib/_G2lib_Interpolation.cpython-38-x86_64-linux-gnu.so
G2lib/_G2lib_Interpolation.cpython-39-x86_64-linux-gnu.so
G2lib/__init__.py
G2lib.egg-info/PKG-INFO
G2lib.egg-info/SOURCES.txt
G2lib.egg-info/dependency_links.txt
G2lib.egg-info/not-zip-safe
G2lib.egg-info/requires.txt
G2lib.egg-info/top_level.txt