Metadata-Version: 2.1
Name: G2lib
Version: 3.1.0.post2
Summary: Geometric manipulation library for curves
Home-page: https://github.com/MatteoRagni/Clothoids-1
Author: Matteo Ragni
Author-email: info@ragni.me
Maintainer: Matteo Ragni
Maintainer-email: info@ragni.me
License: MIT License
Project-URL: Source, https://github.com/MatteoRagni/Clothoids-1
Project-URL: Tracker, https://github.com/MatteoRagni/Clothoids-1
Keywords: Clothoids,Polyline,Biarc,Arc
Classifier: Intended Audience :: Developers
Classifier: License :: OSI Approved :: MIT License
Classifier: Programming Language :: Python
Classifier: Topic :: Scientific/Engineering :: Mathematics
Classifier: Topic :: Software Development :: Libraries
Requires-Python: >=3.6
License-File: LICENSE
Requires-Dist: setuptools
